gssc/__init__.py
gssc/infer.py
gssc/model_prepare.py
gssc/networks.py
gssc/utils.py
gssc/command/__init__.py
gssc/command/com_infer.py
gssc/command/gui.py
gssc/nets/__init__.py
gssc/nets/gru_net_v1.pt
gssc/nets/sig_net_v1.pt
gssc/train/DataManage.py
gssc/train/__init__.py
gssc/train/train.py
gssc-0.0.9.dist-info/LICENSE
gssc-0.0.9.dist-info/METADATA
gssc-0.0.9.dist-info/WHEEL
gssc-0.0.9.dist-info/entry_points.txt
gssc-0.0.9.dist-info/top_level.txt
gssc-0.0.9.dist-info/RECORD
